{
    "name": "Protocapetlus Adlerzi",
    "skills": [
        {
            "category": "pre-combat",
            "name": "Strong Guard",
            "type": "damage_reduction",
            "value": {
                "level_1": 32,
                "level_2": 34,
                "level_3": 36,
                "level_4": 38,
                "level_5": 40
            },
            "target": "self",
            "round": [1,2,3],
            "probability": 100,
            "effect": [],
            "synergy_effect": []
        },
       {
            "category": "combat",
            "name": "Silence Strike",
            "type": "damage",
            "value": {
                "level_1": 180,
                "level_2": 200,
                "level_3": 220,
                "level_4": 240,
                "level_5": 260
            },
            "target": "single_enemy",
            "round": [1,2,3,4,5,6,7,8],
            "probability": 50,
            "effect": [
                {
                    "name": "silence",
                    "duration": 1,
                    "value": null
                }
            ],
            "synergy_effect": []
        },
       {
            "category": "combat",
            "name": "Savage charge",
            "type": "damage",
            "value": {
                "level_1": 180,
                "level_2": 200,
                "level_3": 220,
                "level_4": 240,
                "level_5": 260
            },
            "target": "three_enemies",
            "round": [2,4,7],
            "probability": 100,
            "effect": [],
            "synergy_effect": [
                {
                    "name": "effect_control",
                    "effect": [
                        {
                            "name": "increase_damage_taken",
                            "value": 30
                        }
                    ]
                }
            ]
        }
    ]
  
}